firanka/__init__.py
firanka/builders.py
firanka/exceptions.py
firanka/intervals.py
firanka/ranges.py
firanka/timeproviders.py
firanka/series/__init__.py
firanka/series/base.py
firanka/series/function.py
firanka/series/interpolations.py
firanka/series/modulo.py
firanka-0.1.12.dist-info/DESCRIPTION.rst
firanka-0.1.12.dist-info/METADATA
firanka-0.1.12.dist-info/RECORD
firanka-0.1.12.dist-info/WHEEL
firanka-0.1.12.dist-info/metadata.json
firanka-0.1.12.dist-info/top_level.txt
